{
  "updated_at": "2026-05-24T18:30:27.180733+09:00",
  "keywords": [
    "雑談",
    "朝活",
    "ラジオ"
  ],
  "streams": [
    {
      "id": "01KSAKKYJ964FB0C30YANZPSZ8",
      "title": "【雑談】深夜にまったりチル雑談【渡会雲雀/にじさんじ】",
      "liver_name": "",
      "liver_icon": "",
      "thumbnail": "https://i.ytimg.com/vi/VthrTfxufcY/maxresdefault.jpg",
      "status": "not_on_air",
      "start_time": "2026-05-23T23:30:00.000+09:00",
      "url": "https://www.youtube.com/watch?v=VthrTfxufcY",
      "matched_keywords": [
        "雑談"
      ]
    },
    {
      "id": "01KSA9X42XY9DCA5H3JC4JEGF5",
      "title": "【 雑談 】 寝る前に自語り#Rei7に聞きたい7の事  【 Rei7 / にじさんじ 】",
      "liver_name": "",
      "liver_icon": "",
      "thumbnail": "https://i.ytimg.com/vi/RFwCcPp_igY/maxresdefault.jpg",
      "status": "not_on_air",
      "start_time": "2026-05-23T22:00:00.000+09:00",
      "url": "https://www.youtube.com/watch?v=RFwCcPp_igY",
      "matched_keywords": [
        "雑談"
      ]
    },
    {
      "id": "01KSA71AXNQXKYSWKVZSK0KZ5J",
      "title": "【雑談】一周回ってシンプル雑談じゃない？【渚トラウト/にじさんじ】",
      "liver_name": "01J6CCJAK9N4AKCGFZ75P3W147",
      "liver_icon": "",
      "thumbnail": "https://i.ytimg.com/vi/walzveD_XbE/maxresdefault.jpg",
      "status": "not_on_air",
      "start_time": "2026-05-23T20:00:00.000+09:00",
      "url": "https://www.youtube.com/watch?v=walzveD_XbE",
      "matched_keywords": [
        "雑談"
      ]
    },
    {
      "id": "01KSA70RRNTC2H93W3NJ5R7A5N",
      "title": "【雑談】闇堕ちから救え！みんなのお悩みお焚きあげ配信【健屋花那/にじさんじ】",
      "liver_name": "",
      "liver_icon": "",
      "thumbnail": "https://i.ytimg.com/vi/cwinWOtF2yI/maxresdefault.jpg",
      "status": "not_on_air",
      "start_time": "2026-05-23T20:00:00.000+09:00",
      "url": "https://www.youtube.com/watch?v=cwinWOtF2yI",
      "matched_keywords": [
        "雑談"
      ]
    },
    {
      "id": "01KSA3A8AZ8D3F9C3BHD6SWZ8Y",
      "title": "【復活の雑談】配信できる幸せをかみしめに来た漢【魁星/にじさんじ】",
      "liver_name": "",
      "liver_icon": "",
      "thumbnail": "https://i.ytimg.com/vi/l68qUD4VCK0/maxresdefault.jpg",
      "status": "not_on_air",
      "start_time": "2026-05-23T20:00:00.000+09:00",
      "url": "https://www.youtube.com/watch?v=l68qUD4VCK0",
      "matched_keywords": [
        "雑談"
      ]
    },
    {
      "id": "01KS94DSD9DDAEB3HM8N7AYNR7",
      "title": "【朝活】朝活という名前を口実にただ朝マックが食べたいんだ。【塚原大地 / にじさんじ】",
      "liver_name": "",
      "liver_icon": "",
      "thumbnail": "https://i.ytimg.com/vi/97d6a1Fe5_k/maxresdefault.jpg",
      "status": "not_on_air",
      "start_time": "2026-05-23T10:00:00.000+09:00",
      "url": "https://www.youtube.com/watch?v=97d6a1Fe5_k",
      "matched_keywords": [
        "朝活"
      ]
    },
    {
      "id": "01KS7Y29CAAG3MMXJ5ZRFCVVTV",
      "title": "起きれたら朝雑談！起きれたら朝雑談！起きれたら朝雑談！起きれたら朝雑談！起きれたら朝雑談！起きれたら朝雑談！起きれたら朝雑談！起きれたら朝雑談！起きれたら朝雑談！起きれたら朝雑談！起きれたら朝雑談！",
      "liver_name": "",
      "liver_icon": "",
      "thumbnail": "https://i.ytimg.com/vi/eoX2F3qE2-o/maxresdefault.jpg",
      "status": "not_on_air",
      "start_time": "2026-05-23T08:00:00.000+09:00",
      "url": "https://www.youtube.com/watch?v=eoX2F3qE2-o",
      "matched_keywords": [
        "雑談"
      ]
    },
    {
      "id": "01KS5NDE6PJXK8JNKP1RBYF3NZ",
      "title": "〖深夜ラジオ〗2026年5月23日(土)のにゃルラジ🌙〖猫屋敷美紅 / にじさんじ〗",
      "liver_name": "01K2KXFY4WTXD0E42NN67KG73Q",
      "liver_icon": "",
      "thumbnail": "https://i.ytimg.com/vi/OIMuYEG8P1U/maxresdefault.jpg",
      "status": "not_on_air",
      "start_time": "2026-05-23T00:00:00.000+09:00",
      "url": "https://www.youtube.com/watch?v=OIMuYEG8P1U",
      "matched_keywords": [
        "ラジオ"
      ]
    },
    {
      "id": "01KSCCJ085GDXEE1P2Y5P82522",
      "title": "【振り返り雑談】誕生日ライブ大感謝!!ライブ構成やダンス、オリ曲などのあれこれのお話！！【倉持めると/にじさんじ】",
      "liver_name": "",
      "liver_icon": "",
      "thumbnail": "https://i.ytimg.com/vi/pH4-8nDqsxI/maxresdefault_live.jpg",
      "status": "on_air",
      "start_time": "2026-05-24T18:00:00.000+09:00",
      "url": "https://www.youtube.com/watch?v=pH4-8nDqsxI",
      "matched_keywords": [
        "雑談"
      ]
    },
    {
      "id": "01KSC27MQ5GB0ERZ70EKBDM82Z",
      "title": "【ラジオ】ジョー・力一の空昼ブランコ #94【にじさんじ】",
      "liver_name": "",
      "liver_icon": "",
      "thumbnail": "https://i.ytimg.com/vi/5Bvvgpj41jY/maxresdefault.jpg",
      "status": "not_on_air",
      "start_time": "2026-05-24T14:00:00.000+09:00",
      "url": "https://www.youtube.com/watch?v=5Bvvgpj41jY",
      "matched_keywords": [
        "ラジオ"
      ]
    },
    {
      "id": "01KSANM8582T5JZAKX8C8EHYJA",
      "title": "【#にじフェス】まったりDANCE LIVEを同時視聴＆振り返り雑談🔥【ぽとなる】",
      "liver_name": "01G8WAJSW14QG60M36YBRZ06C7",
      "liver_icon": "",
      "thumbnail": "https://i.ytimg.com/vi/Re7KN_chvHk/maxresdefault.jpg",
      "status": "not_on_air",
      "start_time": "2026-05-24T13:00:00.000+09:00",
      "url": "https://www.youtube.com/watch?v=Re7KN_chvHk",
      "matched_keywords": [
        "雑談"
      ]
    },
    {
      "id": "01KSAFANHNAYADM5GPXRFNJBTH",
      "title": "【朝雑談】朝、あまりに朝【四季凪アキラ/にじさんじ】",
      "liver_name": "",
      "liver_icon": "",
      "thumbnail": "https://i.ytimg.com/vi/QCf9GoIEcnk/maxresdefault.jpg",
      "status": "not_on_air",
      "start_time": "2026-05-24T10:00:00.000+09:00",
      "url": "https://www.youtube.com/watch?v=QCf9GoIEcnk",
      "matched_keywords": [
        "雑談"
      ]
    },
    {
      "id": "01KSAGFA7EBF5YDKC89FCKMHJA",
      "title": "【朝活雑談】朝活のお時間です【ニチアサ！緋八マン！】【にじさんじ/緋八マナ】",
      "liver_name": "",
      "liver_icon": "",
      "thumbnail": "https://i.ytimg.com/vi/dHQEJhCXmA8/maxresdefault.jpg",
      "status": "not_on_air",
      "start_time": "2026-05-24T07:00:00.000+09:00",
      "url": "https://www.youtube.com/watch?v=dHQEJhCXmA8",
      "matched_keywords": [
        "雑談",
        "朝活"
      ]
    },
    {
      "id": "01KS8B7ZP1E6FJGVYNA14DV38W",
      "title": "〖深夜ラジオ〗2026年5月24日(日)のにゃルラジ🌙〖猫屋敷美紅 / にじさんじ〗",
      "liver_name": "01K2KXFY4WTXD0E42NN67KG73Q",
      "liver_icon": "",
      "thumbnail": "https://i.ytimg.com/vi/zk6fll4oN7A/maxresdefault.jpg",
      "status": "not_on_air",
      "start_time": "2026-05-24T00:00:00.000+09:00",
      "url": "https://www.youtube.com/watch?v=zk6fll4oN7A",
      "matched_keywords": [
        "ラジオ"
      ]
    },
    {
      "id": "01KS7CKYK4DPYSJSSYGVE39SA5",
      "title": "【#朝活 】+ #トモコレ💛ゴミ曜日が来ちゃった…！今週も頑張っていってらっしゃいませ💕【ナセラ/にじさんじ🌸🌙】",
      "liver_name": "",
      "liver_icon": "",
      "thumbnail": "https://i.ytimg.com/vi/i8uZXKf1nFw/maxresdefault_live.jpg",
      "status": "not_on_air",
      "start_time": "2026-05-25T07:00:00.000+09:00",
      "url": "https://www.youtube.com/watch?v=i8uZXKf1nFw",
      "matched_keywords": [
        "朝活"
      ]
    },
    {
      "id": "01KSAWG3H0HK83P5MHBYJN8WBT",
      "title": "〖深夜ラジオ〗2026年5月25日(月)のにゃルラジ🌙〖猫屋敷美紅 / にじさんじ〗",
      "liver_name": "01K2KXFY4WTXD0E42NN67KG73Q",
      "liver_icon": "",
      "thumbnail": "https://i.ytimg.com/vi/HGQrvk_QGZg/maxresdefault_live.jpg",
      "status": "not_on_air",
      "start_time": "2026-05-25T00:00:00.000+09:00",
      "url": "https://www.youtube.com/watch?v=HGQrvk_QGZg",
      "matched_keywords": [
        "ラジオ"
      ]
    }
  ]
}