{
  "updated_at": "2026-06-11T14:00:38.202134+09:00",
  "keywords": [
    "雑談",
    "朝活",
    "ラジオ"
  ],
  "streams": [
    {
      "id": "01KTRJEQPKE2VF18RDYH61FNA7",
      "title": "【🗣️雑談】ひっそり８周年を祝いますが多分普通に雑談【にじさんじ/轟京子】",
      "liver_name": "",
      "liver_icon": "",
      "thumbnail": "https://i.ytimg.com/vi/CH0REE7V_8o/maxresdefault.jpg",
      "status": "not_on_air",
      "start_time": "2026-06-10T23:00:00.000+09:00",
      "url": "https://www.youtube.com/watch?v=CH0REE7V_8o",
      "matched_keywords": [
        "雑談"
      ]
    },
    {
      "id": "01KTRKAWKSNA1TA19WAHDH390G",
      "title": "【雑談】歳とって歌って破産した漢【魁星/にじさんじ】",
      "liver_name": "",
      "liver_icon": "",
      "thumbnail": "https://i.ytimg.com/vi/lVzWG1fyClo/maxresdefault.jpg",
      "status": "not_on_air",
      "start_time": "2026-06-10T22:00:00.000+09:00",
      "url": "https://www.youtube.com/watch?v=lVzWG1fyClo",
      "matched_keywords": [
        "雑談"
      ]
    },
    {
      "id": "01KTPGCQKCDN5V5BYX5Q97D2NJ",
      "title": "【雑談】一昨日年が明けたばかりな気がする雑談～06/10早帰り水曜日～【 にじさんじ / 五木左京 】",
      "liver_name": "",
      "liver_icon": "",
      "thumbnail": "https://i.ytimg.com/vi/2jtDXVbasbY/maxresdefault.jpg",
      "status": "not_on_air",
      "start_time": "2026-06-10T19:00:00.000+09:00",
      "url": "https://www.youtube.com/watch?v=2jtDXVbasbY",
      "matched_keywords": [
        "雑談"
      ]
    },
    {
      "id": "01KTR79KYR6BKH697B6GCCKTDN",
      "title": "【雑談】シャンプーする時、立って洗えば後ろに気配を感じない【にじさんじ/矢車りね】",
      "liver_name": "",
      "liver_icon": "",
      "thumbnail": "https://i.ytimg.com/vi/laZJa5ijhTU/maxresdefault.jpg",
      "status": "not_on_air",
      "start_time": "2026-06-10T17:30:00.000+09:00",
      "url": "https://www.youtube.com/watch?v=laZJa5ijhTU",
      "matched_keywords": [
        "雑談"
      ]
    },
    {
      "id": "01KTPJ3MWD9H5JEXEZ5S18TGZA",
      "title": "【朝活雑談】元気チャージ雑談！！！！！【早乙女ベリー/にじさんじ】",
      "liver_name": "01J6CCJAK9N4AKCGFZ75P3W147",
      "liver_icon": "",
      "thumbnail": "https://i.ytimg.com/vi/xh-ky2wpmyM/maxresdefault.jpg",
      "status": "not_on_air",
      "start_time": "2026-06-10T08:00:00.000+09:00",
      "url": "https://www.youtube.com/watch?v=xh-ky2wpmyM",
      "matched_keywords": [
        "雑談",
        "朝活"
      ]
    },
    {
      "id": "01KTQ790M1271GH9QV49NTBYR9",
      "title": "【朝活】おはすず6月10日（水）＃543【七瀬すず菜/にじさんじ】",
      "liver_name": "01J6CCJAK9N4AKCGFZ75P3W147",
      "liver_icon": "",
      "thumbnail": "https://i.ytimg.com/vi/PdRaFODVKos/maxresdefault.jpg",
      "status": "not_on_air",
      "start_time": "2026-06-10T07:10:00.000+09:00",
      "url": "https://www.youtube.com/watch?v=PdRaFODVKos",
      "matched_keywords": [
        "朝活"
      ]
    },
    {
      "id": "01KTPDGD9NQ540VG64DY27N56Q",
      "title": "【朝活#379】寝ても寝てもいくらでも眠れる気がする6月【雪城眞尋/にじさんじ】",
      "liver_name": "",
      "liver_icon": "",
      "thumbnail": "https://i.ytimg.com/vi/IH1qISF3JRs/maxresdefault.jpg",
      "status": "not_on_air",
      "start_time": "2026-06-10T07:00:00.000+09:00",
      "url": "https://www.youtube.com/watch?v=IH1qISF3JRs",
      "matched_keywords": [
        "朝活"
      ]
    },
    {
      "id": "01KTQ1V7AR2M5ECCWP4QKYHXXX",
      "title": "【 雑談 】おはよ！一緒に朝のまったり時間🌞【 皇れお / にじさんじ 】",
      "liver_name": "01K5BBDKSPBQHW595ESQWN8BBP",
      "liver_icon": "",
      "thumbnail": "https://i.ytimg.com/vi/pd745fKIYYo/maxresdefault.jpg",
      "status": "not_on_air",
      "start_time": "2026-06-10T06:30:00.000+09:00",
      "url": "https://www.youtube.com/watch?v=pd745fKIYYo",
      "matched_keywords": [
        "雑談"
      ]
    },
    {
      "id": "01KTPDTB11ZRQ6GCDM69RH3C3M",
      "title": "〖深夜ラジオ〗2026年6月10日(水)のにゃルラジ🌙〖猫屋敷美紅 / にじさんじ〗",
      "liver_name": "01K2KXFY4WTXD0E42NN67KG73Q",
      "liver_icon": "",
      "thumbnail": "https://i.ytimg.com/vi/Ebt4gD2vtAE/maxresdefault.jpg",
      "status": "not_on_air",
      "start_time": "2026-06-10T00:15:00.000+09:00",
      "url": "https://www.youtube.com/watch?v=Ebt4gD2vtAE",
      "matched_keywords": [
        "ラジオ"
      ]
    },
    {
      "id": "01KTS7Y8B1DDF7KANP7KP0D4AS",
      "title": "【製麺雑談】２０万記念麺へ向け、小野式製麵機初陣！！【一橋綾人/にじさんじ】",
      "liver_name": "",
      "liver_icon": "",
      "thumbnail": "https://i.ytimg.com/vi/C3LTOqySUio/maxresdefault_live.jpg",
      "status": "not_on_air",
      "start_time": "2026-06-11T21:00:00.000+09:00",
      "url": "https://www.youtube.com/watch?v=C3LTOqySUio",
      "matched_keywords": [
        "雑談"
      ]
    },
    {
      "id": "01KTSC7BRNHQDCY3YZF1WHWF10",
      "title": "【雑談】hello america",
      "liver_name": "",
      "liver_icon": "",
      "thumbnail": null,
      "status": "not_on_air",
      "start_time": "2026-06-11T09:00:00.000+09:00",
      "url": "https://www.youtube.com/watch?v=Mpar_cOwnb0",
      "matched_keywords": [
        "雑談"
      ]
    },
    {
      "id": "01KTSTGT3HZ254V8PJAF8NX86C",
      "title": "【雑談】おはよう【明楽レイ/にじさんじ】",
      "liver_name": "",
      "liver_icon": "",
      "thumbnail": "https://i.ytimg.com/vi/-LvFSomUa8U/maxresdefault.jpg",
      "status": "not_on_air",
      "start_time": "2026-06-11T07:30:00.000+09:00",
      "url": "https://www.youtube.com/watch?v=-LvFSomUa8U",
      "matched_keywords": [
        "雑談"
      ]
    },
    {
      "id": "01KTSQYT4DA3RJCRTF68AS5E86",
      "title": "【朝活】おはすず6月11日（木）＃544【七瀬すず菜/にじさんじ】",
      "liver_name": "01J6CCJAK9N4AKCGFZ75P3W147",
      "liver_icon": "",
      "thumbnail": "https://i.ytimg.com/vi/idNlXdH3oFI/maxresdefault.jpg",
      "status": "not_on_air",
      "start_time": "2026-06-11T07:00:00.000+09:00",
      "url": "https://www.youtube.com/watch?v=idNlXdH3oFI",
      "matched_keywords": [
        "朝活"
      ]
    },
    {
      "id": "01KTS0729ZD47C4BA0TW232J6F",
      "title": "〖深夜ラジオ〗2026年6月12日(金)のにゃルラジ🌙〖猫屋敷美紅 / にじさんじ〗",
      "liver_name": "01K2KXFY4WTXD0E42NN67KG73Q",
      "liver_icon": "",
      "thumbnail": "https://i.ytimg.com/vi/1_SaEr-ydxU/maxresdefault_live.jpg",
      "status": "not_on_air",
      "start_time": "2026-06-11T00:00:00.000+09:00",
      "url": "https://www.youtube.com/watch?v=1_SaEr-ydxU",
      "matched_keywords": [
        "ラジオ"
      ]
    },
    {
      "id": "01KTPKHDWWG5264E2H5ZJFWNJS",
      "title": "〖深夜ラジオ〗2026年6月11日(木)のにゃルラジ🌙〖猫屋敷美紅 / にじさんじ〗",
      "liver_name": "01K2KXFY4WTXD0E42NN67KG73Q",
      "liver_icon": "",
      "thumbnail": "https://i.ytimg.com/vi/35D-f19ZyxA/maxresdefault.jpg",
      "status": "not_on_air",
      "start_time": "2026-06-11T00:00:00.000+09:00",
      "url": "https://www.youtube.com/watch?v=35D-f19ZyxA",
      "matched_keywords": [
        "ラジオ"
      ]
    }
  ]
}